mamkit/__init__.py
mamkit/version.py
mamkit/configs/__init__.py
mamkit/configs/audio.py
mamkit/configs/base.py
mamkit/configs/text.py
mamkit/configs/text_audio.py
mamkit/data/__init__.py
mamkit/data/collators.py
mamkit/data/datasets.py
mamkit/data/processing.py
mamkit/models/__init__.py
mamkit/models/audio.py
mamkit/models/text.py
mamkit/models/text_audio.py
mamkit/modules/__init__.py
mamkit/modules/rnn.py
mamkit/modules/transformer.py
mamkit/utility/__init__.py
mamkit/utility/callbacks.py
mamkit/utility/collators.py
mamkit/utility/config.py
mamkit/utility/data.py
mamkit/utility/metrics.py
mamkit/utility/model.py
mamkit/utility/processing.py
mamkit-0.1.2.dist-info/LICENSE
mamkit-0.1.2.dist-info/METADATA
mamkit-0.1.2.dist-info/WHEEL
mamkit-0.1.2.dist-info/top_level.txt
mamkit-0.1.2.dist-info/RECORD
