Metadata-Version: 2.1
Name: mamkit
Version: 0.1.2
Summary: A Comprehensive Multimodal Argument Mining Toolkit. 
Home-page: https://github.com/lt-nlp-lab-unibo/mamkit
Author: Eleonora Mancini, Federico Ruggeri
Author-email: e.mancini@unibo.it
License: MIT
Project-URL: Bug Tracker, https://github.com/lt-nlp-lab-unibo/mamkit/issues
Classifier: Programming Language :: Python :: 3
Classifier: Operating System :: OS Independent
Requires-Python: >=3.10, <3.11
License-File: LICENSE
Requires-Dist: numpy ~=1.26.4
Requires-Dist: resampy ==0.4.3
Requires-Dist: scikit-image ==0.19.2
Requires-Dist: librosa ==0.9.1
Requires-Dist: nltk ~=3.9.1
Requires-Dist: pandas ~=2.2.2
Requires-Dist: pydub ==0.25.1
Requires-Dist: torch ==2.3.0
Requires-Dist: torchaudio ==2.3.0
Requires-Dist: torchmetrics ~=1.4.1
Requires-Dist: torchtext ==0.18.0
Requires-Dist: tqdm ~=4.66.5
Requires-Dist: transformers ~=4.48.0
Requires-Dist: yt-dlp ==2025.3.27
Requires-Dist: Django ~=5.1.3
Requires-Dist: setuptools ~=59.6.0
Requires-Dist: simplejson ==3.20.1
Requires-Dist: httpx ==0.28.1
Requires-Dist: lightning ==2.5.0.post0
